calculator/__init__.py
calculator/calculator.py
fkriza_calculator-1.0.1.dist-info/METADATA
fkriza_calculator-1.0.1.dist-info/WHEEL
fkriza_calculator-1.0.1.dist-info/top_level.txt
fkriza_calculator-1.0.1.dist-info/RECORD
