Metadata-Version: 2.1
Name: fkriza-calculator
Version: 1.0.1
Summary: This Module implements a simple calculator interface with in instance memory,
Author: Filip Křížan
